{
	"systeminfo": "AVX = 1 | AVX2 = 1 | AVX512 = 0 | FMA = 1 | NEON = 0 | ARM_FMA = 0 | METAL = 0 | F16C = 1 | FP16_VA = 0 | WASM_SIMD = 0 | BLAS = 0 | SSE3 = 1 | SSSE3 = 1 | VSX = 0 | CUDA = 0 | COREML = 0 | OPENVINO = 0 | ",
	"model": {
		"type": "base",
		"multilingual": false,
		"vocab": 51864,
		"audio": {
			"ctx": 1500,
			"state": 512,
			"head": 8,
			"layer": 6
		},
		"text": {
			"ctx": 448,
			"state": 512,
			"head": 8,
			"layer": 6
		},
		"mels": 80,
		"ftype": 1
	},
	"params": {
		"model": "models/ggml-base.en.bin",
		"language": "en",
		"translate": false
	},
	"result": {
		"language": "en"
	},
	"transcription": [
		{
			"timestamps": {
				"from": "00:00:00,000",
				"to": "00:00:05,880"
			},
			"offsets": {
				"from": 0,
				"to": 5880
			},
			"text": " Wasmage is a lightweight, high performance and extensible web assembly run time for cloud"
		},
		{
			"timestamps": {
				"from": "00:00:05,880",
				"to": "00:00:09,160"
			},
			"offsets": {
				"from": 5880,
				"to": 9160
			},
			"text": " native edge and decentralized applications."
		},
		{
			"timestamps": {
				"from": "00:00:09,160",
				"to": "00:00:14,800"
			},
			"offsets": {
				"from": 9160,
				"to": 14800
			},
			"text": " It powers serverless apps, embedded functions, microservices, UDF, smart contracts and IoT"
		},
		{
			"timestamps": {
				"from": "00:00:14,800",
				"to": "00:00:15,800"
			},
			"offsets": {
				"from": 14800,
				"to": 15800
			},
			"text": " devices."
		},
		{
			"timestamps": {
				"from": "00:00:15,800",
				"to": "00:00:20,160"
			},
			"offsets": {
				"from": 15800,
				"to": 20160
			},
			"text": " The Wasmage run time provides a well-defined execution sandbox for its contained web assembly"
		},
		{
			"timestamps": {
				"from": "00:00:20,160",
				"to": "00:00:25,240"
			},
			"offsets": {
				"from": 20160,
				"to": 25240
			},
			"text": " byte code program that run time offers isolation and protection for operating system resources."
		}
	]
}
